assets/html-log/prism.css
assets/html-log/prism.js
assets/html-log/semantic.min.css
assets/html-log/semantic.min.js
gluetool/__init__.py
gluetool/action.py
gluetool/color.py
gluetool/core.moduleinfo
gluetool/glue.py
gluetool/help.py
gluetool/html_log.py
gluetool/log.py
gluetool/proxy.py
gluetool/py.typed
gluetool/pylint/__init__.py
gluetool/pylint/option_default.py
gluetool/pylint/shared_defined.py
gluetool/pylint/unknown_option.py
gluetool/result.py
gluetool/sentry.py
gluetool/tests/__init__.py
gluetool/tests/assets/parse_config/configroot/config/data_config_root_a
gluetool/tests/assets/parse_config/configroot/config/data_config_root_b
gluetool/tests/assets/parse_config/configroot/config/data_not_unicode
gluetool/tests/assets/parse_config/configroota/config/data_config_root_a
gluetool/tests/assets/parse_config/configrootb/config/data_config_root_b
gluetool/tests/conftest.py
gluetool/tests/test_core.py
gluetool/tests/test_error.py
gluetool/tests/test_eval_context.py
gluetool/tests/test_help.py
gluetool/tests/test_json.py
gluetool/tests/test_load_yaml.py
gluetool/tests/test_log_exception.py
gluetool/tests/test_logging.py
gluetool/tests/test_module_discovery.py
gluetool/tests/test_new_xml_element.py
gluetool/tests/test_normalize_option.py
gluetool/tests/test_option.py
gluetool/tests/test_parse_config.py
gluetool/tests/test_pipeline_step.py
gluetool/tests/test_render_template.py
gluetool/tests/test_requests.py
gluetool/tests/test_result.py
gluetool/tests/test_run_command.py
gluetool/tests/test_run_modules.py
gluetool/tests/test_tool.py
gluetool/tests/test_treat_url.py
gluetool/tests/test_utils.py
gluetool/tests/test_wait.py
gluetool/tool.py
gluetool/utils.py
gluetool/version.py
gluetool_modules/__init__.py
gluetool_modules/bash_completion.py
gluetool_modules/dep_list.py
gluetool_modules/yaml_pipeline.py
gluetool-2.19.dist-info/METADATA
gluetool-2.19.dist-info/WHEEL
gluetool-2.19.dist-info/entry_points.txt
gluetool-2.19.dist-info/RECORD
