Metadata-Version: 2.1
Name: gluetool
Version: 2.19
Summary: Python framework for constructing command-line pipelines.
Home-page: https://gluetool.readthedocs.org/
License: BSD
Author: Milos Prchlik
Author-email: mprchlik@redhat.com
Requires-Python: >=3.8,<3.10
Classifier: Development Status :: 5 - Production/Stable
Classifier: Environment :: Console
Classifier: Intended Audience :: Developers
Classifier: Intended Audience :: System Administrators
Classifier: License :: OSI Approved :: BSD License
Classifier: License :: Other/Proprietary License
Classifier: Operating System :: POSIX :: Linux
Classifier: Programming Language :: Python :: 3
Classifier: Programming Language :: Python :: 3.8
Classifier: Programming Language :: Python :: 3.9
Classifier: Programming Language :: Python :: 3.7
Classifier: Programming Language :: Python :: 3.8
Classifier: Programming Language :: Python :: 3.9
Classifier: Programming Language :: Python :: Implementation :: CPython
Classifier: Topic :: Software Development :: Libraries :: Application Frameworks
Classifier: Topic :: Utilities
Requires-Dist: Jinja2 (>=3.0.0,<4.0.0)
Requires-Dist: MarkupSafe (>=2.0.0,<3.0.0)
Requires-Dist: Sphinx (>=5.0.0,<6.0.0)
Requires-Dist: attrs (>=23.1.0,<24.0.0)
Requires-Dist: beautifulsoup4
Requires-Dist: cattrs (>=23.2.0,<24.0.0)
Requires-Dist: colorama
Requires-Dist: configparser
Requires-Dist: docutils
Requires-Dist: lxml
Requires-Dist: mock
Requires-Dist: mypy-extensions
Requires-Dist: packaging
Requires-Dist: psutil (>=5.9.5,<6.0.0)
Requires-Dist: requests
Requires-Dist: requests-toolbelt
Requires-Dist: ruamel.yaml (>=0.16.12,<0.17.0)
Requires-Dist: sentry-sdk (>=1.30.0,<2.0.0)
Requires-Dist: six
Requires-Dist: tabulate
Requires-Dist: urlnormalizer
Requires-Dist: zipp
Project-URL: Repository, https://gitlab.com/testing-farm/gluetool
